{
  "legislative_session": "83",
  "identifier": "AJR11",
  "title": "Urges Congress to enact the Protecting the Right to Organize Act. (BDR\u00a0R-1012)",
  "from_organization": "~{\"classification\": \"lower\"}",
  "classification": [
    "bill"
  ],
  "subject": [],
  "abstracts": [],
  "other_titles": [
    {
      "note": "",
      "title": "Urging Congress to enact the Protecting the Right to Organize Act."
    }
  ],
  "other_identifiers": [],
  "actions": [
    {
      "description": "Resolution read. Referred to Committee on Legislative Operations and Elections. To printer.",
      "date": "2025-03-12T07:00:00+00:00",
      "organization_id": "~{\"classification\": \"lower\"}",
      "classification": [],
      "related_entities": [],
      "_processing": {
        "log_file_created": "2025-10-24T23:14:04Z"
      }
    },
    {
      "description": "From printer. To committee.",
      "date": "2025-03-13T07:00:00+00:00",
      "organization_id": "~{\"classification\": \"lower\"}",
      "classification": [],
      "related_entities": [],
      "_processing": {
        "log_file_created": "2025-10-24T23:14:04Z"
      }
    },
    {
      "description": "From committee: Do pass.",
      "date": "2025-04-14T07:00:00+00:00",
      "organization_id": "~{\"classification\": \"lower\"}",
      "classification": [
        "committee-passage"
      ],
      "related_entities": [],
      "_processing": {
        "log_file_created": "2025-10-24T23:14:04Z"
      }
    },
    {
      "description": "Resolution read. Passed. Title approved. Preamble adopted. (Yeas:\u00a027, Nays:\u00a015.) To Senate.\rIn Senate.",
      "date": "2025-04-15T07:00:00+00:00",
      "organization_id": "~{\"classification\": \"lower\"}",
      "classification": [],
      "related_entities": [],
      "_processing": {
        "log_file_created": "2025-10-24T23:14:04Z"
      }
    },
    {
      "description": "Resolution read. Referred to Committee on Legislative Operations and Elections. To committee.",
      "date": "2025-04-16T07:00:00+00:00",
      "organization_id": "~{\"classification\": \"lower\"}",
      "classification": [],
      "related_entities": [],
      "_processing": {
        "log_file_created": "2025-10-24T23:14:04Z"
      }
    },
    {
      "description": "From committee: Do pass.\rPlaced on Resolution File.\rTaken from Resolution File. Placed on Resolution File for next legislative day.",
      "date": "2025-05-19T07:00:00+00:00",
      "organization_id": "~{\"classification\": \"lower\"}",
      "classification": [
        "committee-passage"
      ],
      "related_entities": [],
      "_processing": {
        "log_file_created": "2025-10-24T23:14:04Z"
      }
    },
    {
      "description": "Taken from Resolution File. Placed on Resolution File for next legislative day.",
      "date": "2025-05-20T07:00:00+00:00",
      "organization_id": "~{\"classification\": \"lower\"}",
      "classification": [],
      "related_entities": [],
      "_processing": {
        "log_file_created": "2025-10-24T23:14:04Z"
      }
    },
    {
      "description": "Taken from Resolution File. Placed on Resolution File for next legislative day.",
      "date": "2025-05-21T07:00:00+00:00",
      "organization_id": "~{\"classification\": \"lower\"}",
      "classification": [],
      "related_entities": [],
      "_processing": {
        "log_file_created": "2025-10-24T23:14:04Z"
      }
    },
    {
      "description": "Resolution read. Passed. Title approved. Preamble adopted. (Yeas:\u00a013, Nays:\u00a08.) To Assembly.",
      "date": "2025-05-22T07:00:00+00:00",
      "organization_id": "~{\"classification\": \"lower\"}",
      "classification": [],
      "related_entities": [],
      "_processing": {
        "log_file_created": "2025-10-24T23:14:04Z"
      }
    },
    {
      "description": "In Assembly. To enrollment.",
      "date": "2025-05-23T07:00:00+00:00",
      "organization_id": "~{\"classification\": \"lower\"}",
      "classification": [
        "passage"
      ],
      "related_entities": [],
      "_processing": {
        "log_file_created": "2025-10-24T23:14:04Z"
      }
    },
    {
      "description": "Enrolled and delivered to Secretary of State.\rFile No. 20.",
      "date": "2025-05-27T07:00:00+00:00",
      "organization_id": "~{\"classification\": \"lower\"}",
      "classification": [
        "enrolled"
      ],
      "related_entities": [],
      "_processing": {
        "log_file_created": "2025-10-24T23:14:04Z"
      }
    }
  ],
  "sponsorships": [
    {
      "name": "Reuben D'Silva",
      "classification": "sponsor",
      "entity_type": "person",
      "primary": true,
      "person_id": "~{\"chamber\": \"lower\", \"name\": \"Reuben D'Silva\"}",
      "organization_id": null
    }
  ],
  "related_bills": [],
  "versions": [
    {
      "note": "As Introduced",
      "links": [
        {
          "url": "https://www.leg.state.nv.us/Session/83rd2025/Bills/AJR/AJR11.pdf",
          "media_type": "application/pdf"
        }
      ],
      "date": "",
      "classification": ""
    },
    {
      "note": "As Enrolled",
      "links": [
        {
          "url": "https://www.leg.state.nv.us/Session/83rd2025/Bills/AJR/AJR11_EN.pdf",
          "media_type": "application/pdf"
        }
      ],
      "date": "",
      "classification": ""
    }
  ],
  "documents": [
    {
      "note": "AJR 11_Work Session_H Pepper Sturm_Senior Principal Policy Analyst_Nevada Legislative Counsel Bureau_Research Division",
      "links": [
        {
          "url": "https://www.leg.state.nv.us/App/NELIS/REL/83rd2025/ExhibitDocument/OpenExhibitDocument?exhibitId=77959&fileDownloadName=AJR11WSD.pdf",
          "media_type": "application/pdf"
        }
      ],
      "date": "",
      "classification": ""
    },
    {
      "note": "AJR 11_Opposition_Nancy Carlson",
      "links": [
        {
          "url": "https://www.leg.state.nv.us/App/NELIS/REL/83rd2025/ExhibitDocument/OpenExhibitDocument?exhibitId=77015&fileDownloadName=AJR11_Opposition_NancyCarlson.pdf",
          "media_type": "application/pdf"
        }
      ],
      "date": "",
      "classification": ""
    },
    {
      "note": "AJR11_Support_Nevada State Education Association",
      "links": [
        {
          "url": "https://www.leg.state.nv.us/App/NELIS/REL/83rd2025/ExhibitDocument/OpenExhibitDocument?exhibitId=76900&fileDownloadName=AJR11_Support_NevadaStateEducationAssociation.pdf",
          "media_type": "application/pdf"
        }
      ],
      "date": "",
      "classification": ""
    },
    {
      "note": "AJR11 Work Session Document",
      "links": [
        {
          "url": "https://www.leg.state.nv.us/App/NELIS/REL/83rd2025/ExhibitDocument/OpenExhibitDocument?exhibitId=76267&fileDownloadName=AJR11_WS_doc.pdf",
          "media_type": "application/pdf"
        }
      ],
      "date": "",
      "classification": ""
    },
    {
      "note": "Pro Act Snapshot - submitted by the AFL-CIO",
      "links": [
        {
          "url": "https://www.leg.state.nv.us/App/NELIS/REL/83rd2025/ExhibitDocument/OpenExhibitDocument?exhibitId=75278&fileDownloadName=AJR11_0403_DSilva.R_doc.pdf",
          "media_type": "application/pdf"
        }
      ],
      "date": "",
      "classification": ""
    },
    {
      "note": "AJR11 Testimony in Support - submitted by Paula Catha",
      "links": [
        {
          "url": "https://www.leg.state.nv.us/App/NELIS/REL/83rd2025/ExhibitDocument/OpenExhibitDocument?exhibitId=79076&fileDownloadName=AJR11_Catha.P_supltr.pdf",
          "media_type": "application/pdf"
        }
      ],
      "date": "",
      "classification": ""
    },
    {
      "note": "AJR11 Letter in Support",
      "links": [
        {
          "url": "https://www.leg.state.nv.us/App/NELIS/REL/83rd2025/ExhibitDocument/OpenExhibitDocument?exhibitId=75279&fileDownloadName=AJR11_Daly.C_supltr.pdf",
          "media_type": "application/pdf"
        }
      ],
      "date": "",
      "classification": ""
    }
  ],
  "citations": [],
  "sources": [
    {
      "url": "https://www.leg.state.nv.us/App/NELIS/REL/83rd2025/Bill/12592/Overview",
      "note": ""
    }
  ],
  "extras": {
    "BDR": "R-1012"
  },
  "jurisdiction": {
    "id": "ocd-jurisdiction/country:us/state:nv/government",
    "name": "Nevada",
    "classification": "state",
    "division_id": "ocd-division/country:us/state:nv"
  },
  "_processing": {
    "logs_latest_update": "2025-10-24T23:14:04Z",
    "text_extraction_latest_update": "2025-10-25T10:56:19.796795Z"
  }
}