{
  "legislative_session": "83",
  "identifier": "SB105",
  "title": "Revises provisions relating to Medicare supplemental policies. (BDR\u00a057-71)",
  "from_organization": "~{\"classification\": \"upper\"}",
  "classification": [
    "bill"
  ],
  "subject": [],
  "abstracts": [],
  "other_titles": [
    {
      "note": "",
      "title": "AN ACT relating to insurance; requiring insurers to make available to certain persons all Medicare supplemental policies sold by the insurer that can be purchased by the person; prohibiting an insurer from treating Medicare supplemental policies that are classified as guaranteed issue differently for certain purposes relating to the payment of commissions; and providing other matters properly relating thereto."
    }
  ],
  "other_identifiers": [],
  "actions": [
    {
      "description": "Prefiled. Referred to Committee on Commerce and Labor. To printer.",
      "date": "2025-01-21T08:00:00+00:00",
      "organization_id": "~{\"classification\": \"upper\"}",
      "classification": [
        "introduction",
        "referral-committee"
      ],
      "related_entities": [],
      "_processing": {
        "log_file_created": "2025-10-24T23:14:02Z"
      }
    },
    {
      "description": "From printer.",
      "date": "2025-01-24T08:00:00+00:00",
      "organization_id": "~{\"classification\": \"upper\"}",
      "classification": [],
      "related_entities": [],
      "_processing": {
        "log_file_created": "2025-10-24T23:14:02Z"
      }
    },
    {
      "description": "Read first time. To committee.",
      "date": "2025-02-03T08:00:00+00:00",
      "organization_id": "~{\"classification\": \"upper\"}",
      "classification": [
        "reading-1"
      ],
      "related_entities": [],
      "_processing": {
        "log_file_created": "2025-10-24T23:14:02Z"
      }
    },
    {
      "description": "(Pursuant to Joint Standing Rule No. 14.3.1, no further action allowed.)",
      "date": "2025-04-12T07:00:00+00:00",
      "organization_id": "~{\"classification\": \"upper\"}",
      "classification": [],
      "related_entities": [],
      "_processing": {
        "log_file_created": "2025-10-24T23:14:02Z"
      }
    }
  ],
  "sponsorships": [
    {
      "name": "Carrie Ann Buck",
      "classification": "sponsor",
      "entity_type": "person",
      "primary": true,
      "person_id": "~{\"chamber\": \"upper\", \"name\": \"Carrie Ann Buck\"}",
      "organization_id": null
    }
  ],
  "related_bills": [],
  "versions": [
    {
      "note": "As Introduced",
      "links": [
        {
          "url": "https://www.leg.state.nv.us/Session/83rd2025/Bills/SB/SB105.pdf",
          "media_type": "application/pdf"
        }
      ],
      "date": "",
      "classification": ""
    }
  ],
  "documents": [],
  "citations": [],
  "sources": [
    {
      "url": "https://www.leg.state.nv.us/App/NELIS/REL/83rd2025/Bill/11996/Overview",
      "note": ""
    }
  ],
  "extras": {
    "BDR": "57-71"
  },
  "jurisdiction": {
    "id": "ocd-jurisdiction/country:us/state:nv/government",
    "name": "Nevada",
    "classification": "state",
    "division_id": "ocd-division/country:us/state:nv"
  },
  "_processing": {
    "logs_latest_update": "2025-10-24T23:14:02Z"
  }
}