{
  "action": {
    "description": "From printer.\rRead first time. To committee.\rFrom committee: Amend, and do pass as amended.\rPlaced on Second Reading File.\rDeclared an emergency measure under the Constitution.\rRead second time. Amended. (Amend. No. 2.)\rReprinting dispensed with.\rPlaced on General File.\rRead third time. Passed, as amended. Title approved, as amended. (Yeas:\u00a015, Nays:\u00a06.) To printer.",
    "date": "2025-11-13T08:00:00+00:00",
    "organization_id": "~{\"classification\": \"upper\"}",
    "classification": [
      "committee-passage",
      "passage",
      "reading-1",
      "reading-2",
      "reading-3"
    ],
    "related_entities": []
  },
  "bill_id": "SB5"
}