{
  "legislative_session": "83",
  "identifier": "AB103",
  "title": "Revises provisions relating to housing authorities. (BDR\u00a025-554)",
  "from_organization": "~{\"classification\": \"lower\"}",
  "classification": [
    "bill"
  ],
  "subject": [],
  "abstracts": [],
  "other_titles": [
    {
      "note": "",
      "title": "AN ACT relating to housing authorities; authorizing the formation of a regional housing authority in certain counties; setting forth the composition and powers of certain regional housing authorities; revising various provisions relating to housing authorities; revising the compensation of commissioners; and providing other matters properly relating thereto."
    }
  ],
  "other_identifiers": [],
  "actions": [
    {
      "description": "Prefiled. Referred to Committee on Government Affairs. To printer.",
      "date": "2025-01-14T08:00:00+00:00",
      "organization_id": "~{\"classification\": \"lower\"}",
      "classification": [
        "introduction",
        "referral-committee"
      ],
      "related_entities": [],
      "_processing": {
        "log_file_created": "2025-10-24T23:14:03Z"
      }
    },
    {
      "description": "From printer.",
      "date": "2025-01-16T08:00:00+00:00",
      "organization_id": "~{\"classification\": \"lower\"}",
      "classification": [],
      "related_entities": [],
      "_processing": {
        "log_file_created": "2025-10-24T23:14:03Z"
      }
    },
    {
      "description": "Read first time. To committee.",
      "date": "2025-02-04T08:00:00+00:00",
      "organization_id": "~{\"classification\": \"lower\"}",
      "classification": [
        "reading-1"
      ],
      "related_entities": [],
      "_processing": {
        "log_file_created": "2025-10-24T23:14:03Z"
      }
    },
    {
      "description": "From committee: Amend, and do pass as amended.\rPlaced on Second Reading File.\rRead second time. Amended. (Amend. No. 277.)\rDispensed with reprinting.",
      "date": "2025-04-21T07:00:00+00:00",
      "organization_id": "~{\"classification\": \"lower\"}",
      "classification": [
        "committee-passage",
        "reading-2"
      ],
      "related_entities": [],
      "_processing": {
        "log_file_created": "2025-10-24T23:14:03Z"
      }
    },
    {
      "description": "Read third time. Passed, as amended. Title approved, as amended. (Yeas:\u00a042, Nays:\u00a0None.)\rTo printer.",
      "date": "2025-04-22T07:00:00+00:00",
      "organization_id": "~{\"classification\": \"lower\"}",
      "classification": [
        "passage",
        "reading-3"
      ],
      "related_entities": [],
      "_processing": {
        "log_file_created": "2025-10-24T23:14:03Z"
      }
    },
    {
      "description": "From printer. To engrossment. Engrossed. First reprint.\rTo Senate.",
      "date": "2025-04-25T07:00:00+00:00",
      "organization_id": "~{\"classification\": \"lower\"}",
      "classification": [],
      "related_entities": [],
      "_processing": {
        "log_file_created": "2025-10-24T23:14:03Z"
      }
    },
    {
      "description": "In Senate.\rRead first time. Referred to Committee on Government Affairs. To committee.",
      "date": "2025-04-28T07:00:00+00:00",
      "organization_id": "~{\"classification\": \"upper\"}",
      "classification": [
        "reading-1",
        "referral-committee"
      ],
      "related_entities": [],
      "_processing": {
        "log_file_created": "2025-10-24T23:14:03Z"
      }
    },
    {
      "description": "From committee: Do pass.\rPlaced on Second Reading File.\rRead second time.",
      "date": "2025-05-19T07:00:00+00:00",
      "organization_id": "~{\"classification\": \"upper\"}",
      "classification": [
        "committee-passage",
        "reading-2"
      ],
      "related_entities": [],
      "_processing": {
        "log_file_created": "2025-10-24T23:14:03Z"
      }
    },
    {
      "description": "Taken from General File. Placed on General File for next legislative day.",
      "date": "2025-05-20T07:00:00+00:00",
      "organization_id": "~{\"classification\": \"upper\"}",
      "classification": [],
      "related_entities": [],
      "_processing": {
        "log_file_created": "2025-10-24T23:14:03Z"
      }
    },
    {
      "description": "Taken from General File. Placed on General File for next legislative day.",
      "date": "2025-05-21T07:00:00+00:00",
      "organization_id": "~{\"classification\": \"upper\"}",
      "classification": [],
      "related_entities": [],
      "_processing": {
        "log_file_created": "2025-10-24T23:14:03Z"
      }
    },
    {
      "description": "Taken from General File. Placed on General File for next legislative day.",
      "date": "2025-05-22T07:00:00+00:00",
      "organization_id": "~{\"classification\": \"upper\"}",
      "classification": [],
      "related_entities": [],
      "_processing": {
        "log_file_created": "2025-10-24T23:14:03Z"
      }
    },
    {
      "description": "Read third time. Passed. Title approved. (Yeas:\u00a019, Nays:\u00a02.) To Assembly.",
      "date": "2025-05-23T07:00:00+00:00",
      "organization_id": "~{\"classification\": \"upper\"}",
      "classification": [
        "passage",
        "reading-3"
      ],
      "related_entities": [],
      "_processing": {
        "log_file_created": "2025-10-24T23:14:03Z"
      }
    },
    {
      "description": "In Assembly. To enrollment.",
      "date": "2025-05-26T07:00:00+00:00",
      "organization_id": "~{\"classification\": \"lower\"}",
      "classification": [
        "passage"
      ],
      "related_entities": [],
      "_processing": {
        "log_file_created": "2025-10-24T23:14:03Z"
      }
    },
    {
      "description": "Enrolled and delivered to Governor.",
      "date": "2025-05-27T07:00:00+00:00",
      "organization_id": "~{\"classification\": \"executive\"}",
      "classification": [
        "enrolled",
        "executive-receipt"
      ],
      "related_entities": [],
      "_processing": {
        "log_file_created": "2025-10-24T23:14:03Z"
      }
    },
    {
      "description": "Approved by the Governor.\rChapter 104.",
      "date": "2025-05-29T07:00:00+00:00",
      "organization_id": "~{\"classification\": \"executive\"}",
      "classification": [
        "executive-signature"
      ],
      "related_entities": [],
      "_processing": {
        "log_file_created": "2025-10-24T23:14:03Z"
      }
    }
  ],
  "sponsorships": [
    {
      "name": "PK O\u00e2\u0080\u0099Neill",
      "classification": "sponsor",
      "entity_type": "person",
      "primary": true,
      "person_id": "~{\"chamber\": \"lower\", \"name\": \"PK O\\u00e2\\u0080\\u0099Neill\"}",
      "organization_id": null
    },
    {
      "name": "Natha Anderson",
      "classification": "cosponsor",
      "entity_type": "person",
      "primary": false,
      "person_id": "~{\"chamber\": \"lower\", \"name\": \"Natha Anderson\"}",
      "organization_id": null
    }
  ],
  "related_bills": [],
  "versions": [
    {
      "note": "As Introduced",
      "links": [
        {
          "url": "https://www.leg.state.nv.us/Session/83rd2025/Bills/AB/AB103.pdf",
          "media_type": "application/pdf"
        }
      ],
      "date": "",
      "classification": ""
    },
    {
      "note": "Amendment 277",
      "links": [
        {
          "url": "https://www.leg.state.nv.us/Session/83rd2025/Bills/Amendments/A_AB103_277.pdf",
          "media_type": "application/pdf"
        }
      ],
      "date": "",
      "classification": ""
    },
    {
      "note": "Reprint 1",
      "links": [
        {
          "url": "https://www.leg.state.nv.us/Session/83rd2025/Bills/AB/AB103_R1.pdf",
          "media_type": "application/pdf"
        }
      ],
      "date": "",
      "classification": ""
    },
    {
      "note": "As Enrolled",
      "links": [
        {
          "url": "https://www.leg.state.nv.us/Session/83rd2025/Bills/AB/AB103_EN.pdf",
          "media_type": "application/pdf"
        }
      ],
      "date": "",
      "classification": ""
    }
  ],
  "documents": [
    {
      "note": "AB103_Conceptual Amendment_Assemblymember P K O'Neill",
      "links": [
        {
          "url": "https://www.leg.state.nv.us/App/NELIS/REL/83rd2025/ExhibitDocument/OpenExhibitDocument?exhibitId=77598&fileDownloadName=AB103_ConceptualAmendment_Assemblymember_ONeill.pdf",
          "media_type": "application/pdf"
        }
      ],
      "date": "",
      "classification": ""
    },
    {
      "note": "AB 103 Work Session document",
      "links": [
        {
          "url": "https://www.leg.state.nv.us/App/NELIS/REL/83rd2025/ExhibitDocument/OpenExhibitDocument?exhibitId=75971&fileDownloadName=0410_AB103_WS.pdf",
          "media_type": "application/pdf"
        }
      ],
      "date": "",
      "classification": ""
    },
    {
      "note": "AB 103 Amendment submitted by Assemblymember Philip \"PK\" O'Neill",
      "links": [
        {
          "url": "https://www.leg.state.nv.us/App/NELIS/REL/83rd2025/ExhibitDocument/OpenExhibitDocument?exhibitId=74694&fileDownloadName=AB103_0402_Amendment_ONeill.pk.pdf",
          "media_type": "application/pdf"
        }
      ],
      "date": "",
      "classification": ""
    }
  ],
  "citations": [],
  "sources": [
    {
      "url": "https://www.leg.state.nv.us/App/NELIS/REL/83rd2025/Bill/11985/Overview",
      "note": ""
    }
  ],
  "extras": {
    "BDR": "25-554"
  },
  "jurisdiction": {
    "id": "ocd-jurisdiction/country:us/state:nv/government",
    "name": "Nevada",
    "classification": "state",
    "division_id": "ocd-division/country:us/state:nv"
  },
  "_processing": {
    "logs_latest_update": "2025-10-24T23:14:03Z",
    "text_extraction_latest_update": "2025-10-25T09:13:45.707518Z"
  }
}