{
  "legislative_session": "83",
  "identifier": "AB182",
  "title": "Creates the Legislative Committee on the Reduction of Nonessential State Expenditures. (BDR\u00a017-929)",
  "from_organization": "~{\"classification\": \"lower\"}",
  "classification": [
    "bill"
  ],
  "subject": [],
  "abstracts": [],
  "other_titles": [
    {
      "note": "",
      "title": "AN ACT relating to legislative affairs; creating the Legislative Committee on the Reduction of Nonessential State Expenditures; prescribing the powers and duties of the Committee; and providing other matters properly relating thereto."
    }
  ],
  "other_identifiers": [],
  "actions": [
    {
      "description": "Prefiled. Referred to Committee on Legislative Operations and Elections. To printer.",
      "date": "2025-02-02T08:00:00+00:00",
      "organization_id": "~{\"classification\": \"lower\"}",
      "classification": [
        "introduction",
        "referral-committee"
      ],
      "related_entities": [],
      "_processing": {
        "log_file_created": "2025-10-24T23:14:04Z"
      }
    },
    {
      "description": "From printer.\rRead first time. To committee.",
      "date": "2025-02-04T08:00:00+00:00",
      "organization_id": "~{\"classification\": \"lower\"}",
      "classification": [
        "reading-1"
      ],
      "related_entities": [],
      "_processing": {
        "log_file_created": "2025-10-24T23:14:04Z"
      }
    },
    {
      "description": "Notice of eligibility for exemption.",
      "date": "2025-02-12T08:00:00+00:00",
      "organization_id": "~{\"classification\": \"lower\"}",
      "classification": [],
      "related_entities": [],
      "_processing": {
        "log_file_created": "2025-10-24T23:14:04Z"
      }
    },
    {
      "description": "(Pursuant to Joint Standing Rule No. 14.3.1, no further action allowed.)",
      "date": "2025-04-12T07:00:00+00:00",
      "organization_id": "~{\"classification\": \"lower\"}",
      "classification": [],
      "related_entities": [],
      "_processing": {
        "log_file_created": "2025-10-24T23:14:04Z"
      }
    }
  ],
  "sponsorships": [
    {
      "name": "Jill Dickman",
      "classification": "sponsor",
      "entity_type": "person",
      "primary": true,
      "person_id": "~{\"chamber\": \"lower\", \"name\": \"Jill Dickman\"}",
      "organization_id": null
    }
  ],
  "related_bills": [],
  "versions": [
    {
      "note": "As Introduced",
      "links": [
        {
          "url": "https://www.leg.state.nv.us/Session/83rd2025/Bills/AB/AB182.pdf",
          "media_type": "application/pdf"
        }
      ],
      "date": "",
      "classification": ""
    }
  ],
  "documents": [],
  "citations": [],
  "sources": [
    {
      "url": "https://www.leg.state.nv.us/App/NELIS/REL/83rd2025/Bill/12136/Overview",
      "note": ""
    }
  ],
  "extras": {
    "BDR": "17-929"
  },
  "jurisdiction": {
    "id": "ocd-jurisdiction/country:us/state:nv/government",
    "name": "Nevada",
    "classification": "state",
    "division_id": "ocd-division/country:us/state:nv"
  },
  "_processing": {
    "logs_latest_update": "2025-10-24T23:14:04Z"
  }
}